kaos_cli/__init__.py
kaos_cli/install.py
kaos_cli/main.py
kaos_cli/proxy.py
kaos_cli/ui.py
kaos_cli/agent/__init__.py
kaos_cli/agent/deploy.py
kaos_cli/agent/invoke.py
kaos_cli/mcp/__init__.py
kaos_cli/mcp/build.py
kaos_cli/mcp/crud.py
kaos_cli/mcp/deploy.py
kaos_cli/mcp/init.py
kaos_cli/mcp/invoke.py
kaos_cli/modelapi/__init__.py
kaos_cli/modelapi/deploy.py
kaos_cli/modelapi/invoke.py
kaos_cli/system/__init__.py
kaos_cli/system/create_rbac.py
kaos_cli/system/install.py
kaos_cli/system/runtimes.py
kaos_cli/system/status.py
kaos_cli/utils/__init__.py
kaos_cli/utils/crud.py
kaos_cli-0.2.0.dist-info/METADATA
kaos_cli-0.2.0.dist-info/WHEEL
kaos_cli-0.2.0.dist-info/entry_points.txt
kaos_cli-0.2.0.dist-info/top_level.txt
kaos_cli-0.2.0.dist-info/RECORD
