Metadata-Version: 2.4
Name: kaos-cli
Version: 0.2.0
Summary: CLI for KAOS (K8s Agent Orchestration System)
Requires-Python: >=3.12
Requires-Dist: typer>=0.9.0
Requires-Dist: httpx>=0.27.0
Requires-Dist: uvicorn>=0.30.0
Requires-Dist: starlette>=0.37.0
Requires-Dist: kubernetes>=29.0.0
